getsploit/__init__.py
getsploit-2.0.2.dist-info/LICENSE
getsploit-2.0.2.dist-info/METADATA
getsploit-2.0.2.dist-info/WHEEL
getsploit-2.0.2.dist-info/entry_points.txt
getsploit-2.0.2.dist-info/RECORD
