Metadata-Version: 2.3
Name: getsploit
Version: 2.0.2
Summary: Command line search and download tool for Vulners Database inspired by searchsploit.
License: GPL-3.0-or-later
Keywords: security,network,vulners,vulnerability,CVE
Author: Vulners Team
Requires-Python: >=3.10
Classifier: Development Status :: 5 - Production/Stable
Classifier: Operating System :: OS Independent
Classifier: Programming Language :: Python
Classifier: Topic :: Software Development :: Libraries :: Python Modules
Classifier: Intended Audience :: Developers
Classifier: Intended Audience :: Information Technology
Classifier: License :: OSI Approved :: GNU General Public License v3 (GPLv3)
Classifier: Topic :: Software Development :: Version Control
Classifier: Topic :: Utilities
Requires-Dist: click (>=8.2.1,<9.0.0)
Requires-Dist: httpx (>=0.28.1,<1.0.0)
Requires-Dist: orjson (>=3.11.3,<4.0.0)
Requires-Dist: texttable (>=1.7.0,<2.0.0)
